{
  "Massachusetts Institute of Technology (MIT)": {
    "url": "https://www.topuniversities.com/universities/massachusetts-institute-technology-mit",
    "latitude": 42.3592444,
    "longitude": -71.0931389,
    "timestamp": "2025-10-16T05:04:41.278494"
  },
  "Imperial College London": {
    "url": "https://www.topuniversities.com/universities/imperial-college-london",
    "latitude": 51.4992,
    "longitude": -0.174367,
    "timestamp": "2025-10-16T05:04:52.202898"
  },
  "Stanford University": {
    "url": "https://www.topuniversities.com/universities/stanford-university",
    "latitude": 37.4274745,
    "longitude": -122.169719,
    "timestamp": "2025-10-16T05:04:59.673188"
  },
  "University of Oxford": {
    "url": "https://www.topuniversities.com/universities/university-oxford",
    "latitude": 51.7527556,
    "longitude": -1.266146,
    "timestamp": "2025-10-16T05:05:08.229746"
  },
  "Harvard University": {
    "url": "https://www.topuniversities.com/universities/harvard-university",
    "latitude": 42.3770029,
    "longitude": -71.1166601,
    "timestamp": "2025-10-16T05:05:16.140625"
  },
  "University of Cambridge": {
    "url": "https://www.topuniversities.com/universities/university-cambridge",
    "latitude": 52.2052356,
    "longitude": 0.11705,
    "timestamp": "2025-10-16T05:05:23.515940"
  },
  "ETH Zurich (Swiss Federal Institute of Technology)": {
    "url": "https://www.topuniversities.com/universities/eth-zurich",
    "latitude": 47.3765374,
    "longitude": 8.5480861,
    "timestamp": "2025-10-16T05:05:29.632995"
  },
  "National University of Singapore (NUS)": {
    "url": "https://www.topuniversities.com/universities/national-university-singapore-nus",
    "latitude": 1.2971342,
    "longitude": 103.7777567,
    "timestamp": "2025-10-16T05:05:40.512798"
  },
  "UCL (University College London)": {
    "url": "https://www.topuniversities.com/universities/ucl",
    "latitude": 51.5245592,
    "longitude": -0.1340401,
    "timestamp": "2025-10-16T05:05:48.342145"
  },
  "California Institute of Technology (Caltech)": {
    "url": "https://www.topuniversities.com/universities/california-institute-technology-caltech",
    "latitude": 34.1390112,
    "longitude": -118.1245135,
    "timestamp": "2025-10-16T05:05:56.216219"
  }
}